demisto_sdk/__init__.py
demisto_sdk/__main__.py
demisto_sdk/commands/__init__.py
demisto_sdk/commands/common/MDXServer.py
demisto_sdk/commands/common/StrEnum.py
demisto_sdk/commands/common/__init__.py
demisto_sdk/commands/common/clients/__init__.py
demisto_sdk/commands/common/clients/configs.py
demisto_sdk/commands/common/clients/errors.py
demisto_sdk/commands/common/clients/xsiam/xsiam_api_client.py
demisto_sdk/commands/common/clients/xsoar/xsoar_api_client.py
demisto_sdk/commands/common/clients/xsoar_saas/xsoar_saas_api_client.py
demisto_sdk/commands/common/configuration.py
demisto_sdk/commands/common/constants.py
demisto_sdk/commands/common/content/README.md
demisto_sdk/commands/common/content/__init__.py
demisto_sdk/commands/common/content/content.py
demisto_sdk/commands/common/content/docs/CONTRIBUTION.md
demisto_sdk/commands/common/content/errors.py
demisto_sdk/commands/common/content/objects/abstract_objects/__init__.py
demisto_sdk/commands/common/content/objects/abstract_objects/dictionary_based_object.py
demisto_sdk/commands/common/content/objects/abstract_objects/general_object.py
demisto_sdk/commands/common/content/objects/abstract_objects/json_object.py
demisto_sdk/commands/common/content/objects/abstract_objects/text_object.py
demisto_sdk/commands/common/content/objects/abstract_objects/yaml_object.py
demisto_sdk/commands/common/content/objects/pack_objects/__init__.py
demisto_sdk/commands/common/content/objects/pack_objects/abstract_pack_objects/json_content_object.py
demisto_sdk/commands/common/content/objects/pack_objects/abstract_pack_objects/yaml_content_object.py
demisto_sdk/commands/common/content/objects/pack_objects/abstract_pack_objects/yaml_unify_content_object.py
demisto_sdk/commands/common/content/objects/pack_objects/agentix_action/agentix_action.py
demisto_sdk/commands/common/content/objects/pack_objects/agentix_agent/agentix_agent.py
demisto_sdk/commands/common/content/objects/pack_objects/author_image/author_image.py
demisto_sdk-1.38.17.dist-info/LICENSE
demisto_sdk-1.38.17.dist-info/METADATA
demisto_sdk-1.38.17.dist-info/WHEEL
demisto_sdk-1.38.17.dist-info/entry_points.txt
demisto_sdk-1.38.17.dist-info/RECORD
