Metadata-Version: 2.1
Name: demisto-sdk
Version: 1.38.17
Summary: "A Python library for the Demisto SDK"
License: MIT
Author: Demisto
Requires-Python: >=3.9,<3.13
Classifier: Intended Audience :: Developers
Classifier: License :: OSI Approved :: MIT License
Classifier: Natural Language :: English
Classifier: Programming Language :: Python :: 3
Classifier: Programming Language :: Python :: 3.9
Classifier: Programming Language :: Python :: 3.10
Classifier: Programming Language :: Python :: 3.11
Classifier: Programming Language :: Python :: 3.12
Classifier: Programming Language :: Python :: Implementation :: CPython
Provides-Extra: build
Provides-Extra: generate-unit-tests
Requires-Dist: GitPython (>=3.1.37,<4.0.0)
Requires-Dist: Pebble (>=4.6.3,<6.0.0)
Requires-Dist: PyPDF2 (>=1.28.6,<2.0.0)
Requires-Dist: autopep8 (>=2.0.4,<3.0.0)
Requires-Dist: bandit (>=1.7.4,<2.0.0)
Requires-Dist: beautifulsoup4 (>=4.11.1,<5.0.0)
Requires-Dist: chardet (>=4,<6)
Requires-Dist: coloredlogs (>=15.0.1,<16.0.0)
Requires-Dist: configparser (>=5.2.0,<6.0.0)
Requires-Dist: coverage (>=7.2.1,<7.4)
Requires-Dist: dateparser (>=1.1.1,<2.0.0)
Requires-Dist: decorator (>=5.1.1,<6.0.0)
Requires-Dist: demisto-py (>=3.2.21,<4.0.0)
Requires-Dist: dictdiffer (>=0.9.0,<0.10.0)
Requires-Dist: dictor (>=0.1.9,<0.2.0)
Requires-Dist: docker (>=7.1.0,<8.0.0)
Requires-Dist: flatten-dict (>=0.4.2,<0.5.0)
Requires-Dist: gitdb (>=4.0.9,<5.0.0)
Requires-Dist: giturlparse (>=0.10.0,<0.11.0)
Requires-Dist: google-cloud-secret-manager (>=2.18.3,<3.0.0)
Requires-Dist: google-cloud-storage (>=2.13.0,<3.0.0)
Requires-Dist: gsutil (==5.17) ; extra == "build"
Requires-Dist: imagesize (>=1.3.0,<2.0.0)
Requires-Dist: importlib-resources (>=5.6.0,<6.0.0)
Requires-Dist: inflection (>=0.5.1,<0.6.0)
Requires-Dist: jira (>=3.8.0,<4.0.0)
Requires-Dist: json5 (>=0.9.14,<0.10.0)
Requires-Dist: jsonschema (>=4.4.0,<5.0.0)
Requires-Dist: junitparser (>=3.1.0,<4.0.0)
Requires-Dist: klara (>=0.6.3,<0.7.0) ; extra == "generate-unit-tests"
Requires-Dist: loguru (>=0.7.2,<0.8.0)
Requires-Dist: lxml (>=5.0.0,<6.0.0)
Requires-Dist: mergedeep (>=1.3.4,<2.0.0)
Requires-Dist: more-itertools (>=10.0.0,<11.0.0)
Requires-Dist: mypy (>=0.982,<0.983)
Requires-Dist: neo4j (>=5.14.0,<6.0.0)
Requires-Dist: networkx (>=2.7.1,<3.0.0)
Requires-Dist: nltk (==3.9.1)
Requires-Dist: ordered-set (>=4.1.0,<5.0.0)
Requires-Dist: orjson (>=3.8.3,<4.0.0)
Requires-Dist: packaging (>=24.0,<25.0)
Requires-Dist: paramiko (>=3.4.1,<4.0)
Requires-Dist: pre-commit (>=3.5.0,<4.0.0)
Requires-Dist: prettytable (>=3.2.0,<4.0.0)
Requires-Dist: pydantic (>=1.10,<2.0)
Requires-Dist: pygithub (>=2.2.0,<3.0.0)
Requires-Dist: pykwalify (>=1.8.0,<2.0.0)
Requires-Dist: pylint (>=3.3.2,<4.0.0)
Requires-Dist: pyspellchecker (>=0.6.3,<0.7.0)
Requires-Dist: pytest-freezegun (>=0.4.2,<0.5.0)
Requires-Dist: python-dotenv (>=0.20.0,<0.21.0)
Requires-Dist: python-gitlab (>=3.0.0,<4.0.0)
Requires-Dist: requests (>=2.27.1,<3.0.0)
Requires-Dist: ruamel.yaml (>=0.17.21,<0.18.0)
Requires-Dist: setuptools (>=80.9.0)
Requires-Dist: slack-sdk (>=3.17.0,<4.0.0)
Requires-Dist: tabulate (>=0.8.9,<0.10.0)
Requires-Dist: tenacity (>=8.4.1,<9.0.0)
Requires-Dist: toml (>=0.10.2,<0.11.0)
Requires-Dist: typer[all] (>=0.16.0,<0.17.0)
Requires-Dist: typing-extensions (>=4.1.1,<5.0.0)
Requires-Dist: ujson (>=5.1.0,<6.0.0)
Requires-Dist: urllib3 (>=1.26,<3)
Requires-Dist: uv (>=0.1.5,<0.2.0)
Requires-Dist: vulture (>=2.3,<3.0)
Requires-Dist: wcmatch (>=8.3,<9.0)
Requires-Dist: werkzeug (>=3.1.3,<4.0.0)
Requires-Dist: yamlordereddictloader (>=0.4.0,<0.5.0)
